aws_okta_keyman/__init__.py
aws_okta_keyman/__main__.py
aws_okta_keyman/aws.py
aws_okta_keyman/aws_saml.py
aws_okta_keyman/config.py
aws_okta_keyman/duo.py
aws_okta_keyman/keyman.py
aws_okta_keyman/metadata.py
aws_okta_keyman/okta.py
aws_okta_keyman/okta_saml.py
aws_okta_keyman/test/__init__.py
aws_okta_keyman/test/aws_saml_test.py
aws_okta_keyman/test/aws_test.py
aws_okta_keyman/test/config_test.py
aws_okta_keyman/test/duo_test.py
aws_okta_keyman/test/keyman_test.py
aws_okta_keyman/test/main_test.py
aws_okta_keyman/test/metadata_test.py
aws_okta_keyman/test/okta_saml_test.py
aws_okta_keyman/test/okta_test.py
aws_okta_keyman-0.10.0.dist-info/licenses/LICENSE.txt
aws_okta_keyman-0.10.0.dist-info/METADATA
aws_okta_keyman-0.10.0.dist-info/WHEEL
aws_okta_keyman-0.10.0.dist-info/entry_points.txt
aws_okta_keyman-0.10.0.dist-info/top_level.txt
aws_okta_keyman-0.10.0.dist-info/zip-safe
aws_okta_keyman-0.10.0.dist-info/RECORD
