Metadata-Version: 2.4
Name: aws_okta_keyman
Version: 0.10.0
Summary: AWS Okta Keyman
Home-page: https://github.com/nathan-v/aws_okta_keyman
Download-URL: http://pypi.python.org/pypi/aws_okta_keyman#downloads
Author: Nathan V
Author-email: nathan.v@gmail.com
License: Apache License, Version 2.0
Keywords: AWS,Okta,Keys,Auth,Authentication,MFA,Duo,CLI,API
Platform: posix
Platform: nt
Classifier: Development Status :: 4 - Beta
Classifier: Topic :: Software Development
Classifier: Topic :: Internet
Classifier: License :: OSI Approved :: Apache Software License
Classifier: Intended Audience :: Developers
Classifier: Programming Language :: Python :: Implementation :: CPython
Classifier: Programming Language :: Python :: 3.10
Classifier: Programming Language :: Python :: 3.11
Classifier: Programming Language :: Python :: 3.12
Classifier: Programming Language :: Python :: 3.13
Classifier: Programming Language :: Python :: 3.14
Classifier: Operating System :: MacOS :: MacOS X
Classifier: Operating System :: Microsoft :: Windows
Classifier: Operating System :: POSIX
Classifier: Natural Language :: English
Classifier: Environment :: Console
Requires-Python: >=3.10, <4
License-File: LICENSE.txt
Requires-Dist: beautifulsoup4>=4.10.0
Requires-Dist: boto3>=1.4.0
Requires-Dist: colorlog>=4.0.0
Requires-Dist: configparser>=3.5.0
Requires-Dist: keyring>=20.0.0
Requires-Dist: PyYAML>=6.0
Requires-Dist: requests>=2.10.0
Dynamic: author
Dynamic: author-email
Dynamic: classifier
Dynamic: description
Dynamic: description-content-type
Dynamic: download-url
Dynamic: home-page
Dynamic: keywords
Dynamic: license
Dynamic: license-file
Dynamic: platform
Dynamic: requires-dist
Dynamic: requires-python
Dynamic: summary
